<?xml version="1.0" encoding="UTF-8"?>
<definition xmlns:xsi="http://www.w3.org/2001/XMLSchema-instance" version="2">
    <properties>
        <root_name>association</root_name>
        <schema_uri/>
        <namespaces default="">
            <namespace prefix="xsi">http://www.w3.org/2001/XMLSchema-instance</namespace>
            <namespace prefix="dc">http://purl.org/dc/terms/</namespace>
        </namespaces>
    </properties>
    <form>
        <properties>
            <type>form</type>
            <access>true</access>
            <required>true</required>
            <tree>true</tree>
            <actions>
                <create>NULL</create>
                <read>
                    <path>/association</path>
                    <context>document</context>
                </read>
                <update>NULL</update>
                <delete>NULL</delete>
            </actions>
        </properties>
        <children>
            <element name="identification">
                <properties>
                    <type>fieldset</type>
                    <access>TRUE</access>
                    <collapsed>FALSE</collapsed>
                    <collapsible>FALSE</collapsible>
                    <disabled>FALSE</disabled>
                    <executes_submit_callback>FALSE</executes_submit_callback>
                    <multiple>FALSE</multiple>
                    <required>TRUE</required>
                    <resizable>FALSE</resizable>
                    <title>Identification</title>
                    <tree>TRUE</tree>
                    <actions>
                        <create>
                            <path>/association</path>
                            <context>document</context>
                            <schema/>
                            <type>element</type>
                            <prefix>NULL</prefix>
                            <value>identification</value>
                        </create>
                        <read>
                            <path>/association/identification</path>
                            <context>document</context>
                        </read>
                        <update>
                            <path>self::node()</path>
                            <context>self</context>
                        </update>
                        <delete/>
                    </actions>
                </properties>
                <children>
                    <element name="name">
                        <properties>
                            <type>textfield</type>
                            <access>TRUE</access>
                            <collapsed>FALSE</collapsed>
                            <collapsible>FALSE</collapsible>
                            <disabled>FALSE</disabled>
                            <executes_submit_callback>FALSE</executes_submit_callback>
                            <required>TRUE</required>
                            <resizable>FALSE</resizable>
                            <title>Nom</title>
                            <tree>TRUE</tree>
                            <actions>
                                <create>
                                    <path>/association/identification</path>
                                    <context>document</context>
                                    <schema/>
                                    <type>element</type>
                                    <prefix>NULL</prefix>
                                    <value>village</value>
                                </create>
                                <read>
                                    <path>/association/identification/name</path>
                                    <context>document</context>
                                </read>
                                <update>
                                    <path>self::node()</path>
                                    <context>self</context>
                                </update>
                                <delete>NULL</delete>
                            </actions>
                        </properties>
                        <children/>
                    </element>
                </children>
            </element>
            <element name="descriptionGroup">
                <properties>
                    <type>tabs</type>
                    <access>TRUE</access>
                    <collapsed>FALSE</collapsed>
                    <collapsible>FALSE</collapsible>
                    <disabled>FALSE</disabled>
                    <executes_submit_callback>FALSE</executes_submit_callback>
                    <multiple>FALSE</multiple>
                    <required>FALSE</required>
                    <resizable>FALSE</resizable>
                    <title>Description</title>
                    <tree>TRUE</tree>
                </properties>
                <children>
                    <element name="0">
                        <properties>
                            <type>tabpanel</type>
                            <access>TRUE</access>
                            <collapsed>FALSE</collapsed>
                            <collapsible>FALSE</collapsible>
                            <disabled>FALSE</disabled>
                            <executes_submit_callback>FALSE</executes_submit_callback>
                            <multiple>FALSE</multiple>
                            <required>FALSE</required>
                            <resizable>FALSE</resizable>
                            <tree>TRUE</tree>
                            <actions>
                                <create>
                                    <path>self::node()</path>
                                    <context>parent</context>
                                    <schema/>
                                    <type>element</type>
                                    <prefix>NULL</prefix>
                                    <value>descriptionGroup</value>
                                </create>
                                <read>
                                    <path>descriptionGroup</path>
                                    <context>parent</context>
                                </read>
                                <update>
                                    <path>self::node()</path>
                                    <context>self</context>
                                </update>
                                <delete>
                                    <path>self::node()</path>
                                    <context>self</context>
                                </delete>
                            </actions>
                        </properties>
                        <children>
                            <element name="language">
                                <properties>
                                    <type>select</type>
                                    <access>TRUE</access>
                                    <collapsed>FALSE</collapsed>
                                    <collapsible>FALSE</collapsible>
                                    <disabled>FALSE</disabled>
                                    <executes_submit_callback>FALSE</executes_submit_callback>
                                    <description>La langue dans laquelle se fait la description</description>
                                    <default_value>fre</default_value>
                                    <options>
                                        <index key="fre">Francais</index> <!-- Comment changer la valeur pour son code ISO ? -->
                                        <index key="eng">English</index>
                                        <index key="por">Português</index>
                                        <index key="esp">Español</index>
                                    </options>
                                    <multiple>FALSE</multiple>
                                    <required>TRUE</required>
                                    <resizable>FALSE</resizable>
                                    <tree>TRUE</tree>
                                    <actions>
                                        <create>
                                            <path>self::node()</path>
                                            <context>parent</context>
                                            <schema/>
                                            <type>attribute </type>
                                            <prefix>NULL</prefix>
                                            <value>lang</value>
                                        </create>
                                        <read>
                                            <path>lang</path>
                                            <context>parent</context>
                                        </read>
                                        <update>
                                            <path>self::node()</path>
                                            <context>self</context>
                                        </update>
                                        <delete>
                                            <path>self::node()</path>
                                            <context>self</context>
                                        </delete>
                                    </actions>
                                </properties>
                                <children />
                            </element>
                            <element name="description">
                                <properties>
                                    <type>textarea</type>
                                    <access>TRUE</access>
                                    <collapsed>FALSE</collapsed>
                                    <collapsible>FALSE</collapsible>
                                    <disabled>FALSE</disabled>
                                    <executes_submit_callback>FALSE</executes_submit_callback>
                                    <multiple>FALSE</multiple>
                                    <required>FALSE</required>
                                    <resizable>FALSE</resizable>
                                    <title>Description de la ressource</title>
                                    <tree>TRUE</tree>
                                    <actions>
                                        <create>
                                            <path>description</path>
                                            <context>parent</context>
                                            <schema/>
                                            <type>element</type>
                                            <prefix>NULL</prefix>
                                            <value>description</value>
                                        </create>
                                        <read>
                                            <path>description</path>
                                            <context>parent</context>
                                        </read>
                                        <update>
                                            <path>self::node()</path>
                                            <context>self</context>
                                        </update>
                                        <delete>
                                            <path>self::node()</path>
                                            <context>self</context>
                                        </delete>
                                    </actions>
                                </properties>
                                <children/>
                            </element>
                        </children>
                    </element>
                </children>
            </element>
            <element name="link">
                <properties>
                    <type>textfield</type>
                    <access>TRUE</access>
                    <collapsed>FALSE</collapsed>
                    <collapsible>FALSE</collapsible>
                    <disabled>FALSE</disabled>
                    <executes_submit_callback>FALSE</executes_submit_callback>
                    <required>TRUE</required>
                    <resizable>FALSE</resizable>
                    <title>Lien</title>
                    <tree>TRUE</tree>
                    <actions>
                        <create>
                            <path>/association/link</path>
                            <context>document</context>
                            <schema/>
                            <type>attribut</type>
                            <prefix>NULL</prefix>
                            <value>href</value>
                        </create>
                        <read>
                            <path>/association/link/@href</path>
                            <context>document</context>
                        </read>
                        <update>
                            <path>self::node()</path>
                            <context>self</context>
                        </update>
                        <delete>NULL</delete>
                    </actions>
                </properties>
                <children/>
            </element>
            <element name="classification_frame">
                <properties>
                    <type>fieldset</type>
                    <access>TRUE</access>
                    <collapsed>FALSE</collapsed>
                    <collapsible>FALSE</collapsible>
                    <disabled>FALSE</disabled>
                    <executes_submit_callback>FALSE</executes_submit_callback>
                    <multiple>FALSE</multiple>
                    <required>TRUE</required>
                    <resizable>FALSE</resizable>
                    <title>Classification</title>
                    <tree>TRUE</tree>
                    <actions>
                        <create>
                            <path>/association</path>
                            <context>document</context>
                            <schema/>
                            <type>element</type>
                            <prefix>NULL</prefix>
                            <value>classification</value>
                        </create>
                        <read>
                            <path>/association/classification</path>
                            <context>document</context>
                        </read>
                        <update>
                            <path>self::node()</path>
                            <context>self</context>
                        </update>
                        <delete/>
                    </actions>
                </properties>
                <children>
                    <element name="authority">
                        <properties>
                            <type>textfield</type>
                            <access>TRUE</access>
                            <collapsed>FALSE</collapsed>
                            <collapsible>FALSE</collapsible>
                            <disabled>FALSE</disabled>
                            <executes_submit_callback>FALSE</executes_submit_callback>
                            <description>L'origin de la liste de valeurs</description>
                            <required>TRUE</required>
                            <value>???</value>
                            <resizable>FALSE</resizable>
                            <title>Autorité</title>
                            <tree>TRUE</tree>
                            <actions>
                                <create>
                                    <path>self::node()</path>
                                    <context>parent</context>
                                    <schema/>
                                    <type>attribute </type>
                                    <prefix>NULL</prefix>
                                    <value>authority</value>
                                </create>
                                <read>
                                    <path>authority</path>
                                    <context>parent</context>
                                </read>
                                <update>
                                    <path>self::node()</path>
                                    <context>self</context>
                                </update>
                                <delete>
                                    <path>self::node()</path>
                                    <context>self</context>
                                </delete>
                            </actions>
                        </properties>
                        <children />
                    </element>
                    <element name="classification">
                        <properties>
                            <type>tabs</type>
                            <access>TRUE</access>
                            <collapsed>FALSE</collapsed>
                            <collapsible>FALSE</collapsible>
                            <disabled>FALSE</disabled>
                            <executes_submit_callback>FALSE</executes_submit_callback>
                            <multiple>FALSE</multiple>
                            <required>FALSE</required>
                            <resizable>FALSE</resizable>
                            <title>Mots Cles</title>
                            <tree>TRUE</tree>
                        </properties>
                        <children>
                            <element name="0">
                                <properties>
                                    <type>tabpanel</type>
                                    <access>TRUE</access>
                                    <collapsed>FALSE</collapsed>
                                    <collapsible>FALSE</collapsible>
                                    <disabled>FALSE</disabled>
                                    <executes_submit_callback>FALSE</executes_submit_callback>
                                    <multiple>FALSE</multiple>
                                    <required>FALSE</required>
                                    <resizable>FALSE</resizable>
                                    <tree>TRUE</tree>
                                    <actions>
                                        <create>
                                            <path>self::node()</path>
                                            <context>parent</context>
                                            <schema/>
                                            <type>element</type>
                                            <prefix>NULL</prefix>
                                            <value>classification</value>
                                        </create>
                                        <read>
                                            <path>keywordGroup</path>
                                            <context>parent</context>
                                        </read>
                                        <update>
                                            <path>self::node()</path>
                                            <context>self</context>
                                        </update>
                                        <delete/>
                                    </actions>
                                </properties>
                                <children>
                                    <element name="language">
                                        <properties>
                                            <type>select</type>
                                            <access>TRUE</access>
                                            <collapsed>FALSE</collapsed>
                                            <collapsible>FALSE</collapsible>
                                            <disabled>FALSE</disabled>
                                            <executes_submit_callback>FALSE</executes_submit_callback>
                                            <description>La langue du mot cle</description>
                                            <default_value>fre</default_value>
                                            <options>
                                                <index key="fre">Francais</index> <!-- Comment changer la valeur pour son code ISO ? -->
                                                <index key="eng">English</index>
                                                <index key="por">Português</index>
                                                <index key="esp">Español</index>
                                            </options>
                                            <multiple>FALSE</multiple>
                                            <required>TRUE</required>
                                            <resizable>FALSE</resizable>
                                            <tree>TRUE</tree>
                                            <actions>
                                                <create>
                                                    <path>self::node()</path>
                                                    <context>parent</context>
                                                    <schema/>
                                                    <type>attribute </type>
                                                    <prefix>NULL</prefix>
                                                    <value>lang</value>
                                                </create>
                                                <read>
                                                    <path>lang</path>
                                                    <context>parent</context>
                                                </read>
                                                <update>
                                                    <path>self::node()</path>
                                                    <context>self</context>
                                                </update>
                                                <delete>
                                                    <path>self::node()</path>
                                                    <context>self</context>
                                                </delete>
                                            </actions>
                                        </properties>
                                        <children />
                                    </element>
                                    <element name="keyword">
                                        <properties>
                                            <type>tags</type>
                                            <access>TRUE</access>
                                            <collapsed>FALSE</collapsed>
                                            <collapsible>FALSE</collapsible>
                                            <disabled>FALSE</disabled>
                                            <executes_submit_callback>FALSE</executes_submit_callback>
                                            <required>FALSE</required>
                                            <resizable>FALSE</resizable>
                                            <title>Mot cle</title>
                                            <tree>TRUE</tree>
                                        </properties>
                                        <children>
                                            <element name="0">
                                                <properties>
                                                    <type>tag</type>
                                                    <access>TRUE</access>
                                                    <collapsed>FALSE</collapsed>
                                                    <collapsible>FALSE</collapsible>
                                                    <disabled>FALSE</disabled>
                                                    <executes_submit_callback>FALSE</executes_submit_callback>
                                                    <required>FALSE</required>
                                                    <resizable>FALSE</resizable>
                                                    <tree>TRUE</tree>
                                                    <actions>
                                                        <create>
                                                            <path>self::node()</path>
                                                            <context>parent</context>
                                                            <schema/>
                                                            <type>element</type>
                                                            <prefix>NULL</prefix>
                                                            <value>keyword</value>
                                                        </create>
                                                        <read>
                                                            <path>keyword</path>
                                                            <context>parent</context>
                                                        </read>
                                                        <update>
                                                            <path>self::node()</path>
                                                            <context>self</context>
                                                        </update>
                                                        <delete>
                                                            <path>self::node()</path>
                                                            <context>self</context>
                                                        </delete>
                                                    </actions>
                                                </properties>
                                            </element>
                                        </children>
                                    </element>
                                </children>
                            </element>
                        </children>
                    </element>
                </children>
            </element>
        </children>
    </form>
</definition>
